python3_template/.python-version
python3_template/__init__.py
python3_template/console.py
python3_template/wikipedia.py
python3_template-0.1.0.dist-info/entry_points.txt
python3_template-0.1.0.dist-info/LICENSE
python3_template-0.1.0.dist-info/WHEEL
python3_template-0.1.0.dist-info/METADATA
python3_template-0.1.0.dist-info/RECORD
